salt_confd-2022.11.0-py3.9-nspkg.pth
salt_confd/cli.py
salt_confd/confd.sls
salt_confd/parsers.py
salt_confd/scripts.py
salt_confd/version.py
salt_confd-2022.11.0.dist-info/LICENSE
salt_confd-2022.11.0.dist-info/METADATA
salt_confd-2022.11.0.dist-info/WHEEL
salt_confd-2022.11.0.dist-info/entry_points.txt
salt_confd-2022.11.0.dist-info/namespace_packages.txt
salt_confd-2022.11.0.dist-info/top_level.txt
salt_confd-2022.11.0.dist-info/RECORD
